osnap/__init__.py
osnap/__version__.py
osnap/installer.py
osnap/installer_base.py
osnap/installer_mac.py
osnap/installer_win.py
osnap/launchmac.zip
osnap/launchwin-amd64-window.zip
osnap/launchwin-x86-console.zip
osnap/launchwin-x86-window.zip
osnap/logger.py
osnap/make_nsis.py
osnap/make_pkgproj.py
osnap/osnap_testing_support.py
osnap/osnapy.py
osnap/osnapy_base.py
osnap/osnapy_mac.py
osnap/osnapy_win.py
osnap/template.pkgproj
osnap/updater.py
osnap/util.py
osnap-0.3.1.dist-info/LICENSE
osnap-0.3.1.dist-info/LICENSE.txt
osnap-0.3.1.dist-info/METADATA
osnap-0.3.1.dist-info/WHEEL
osnap-0.3.1.dist-info/top_level.txt
osnap-0.3.1.dist-info/RECORD
